ocstrack/__init__.py
ocstrack/_version.py
ocstrack/utils.py
ocstrack/Collocation/__init__.py
ocstrack/Collocation/collocate.py
ocstrack/Collocation/output.py
ocstrack/Collocation/spatial.py
ocstrack/Collocation/temporal.py
ocstrack/Model/__init__.py
ocstrack/Model/model.py
ocstrack/Observation/__init__.py
ocstrack/Observation/argofloat.py
ocstrack/Observation/get_argo.py
ocstrack/Observation/get_sat.py
ocstrack/Observation/satellite.py
ocstrack/Observation/urls.py
ocstrack-0.1.4.post0.dist-info/licenses/LICENSE.txt
ocstrack-0.1.4.post0.dist-info/METADATA
ocstrack-0.1.4.post0.dist-info/WHEEL
ocstrack-0.1.4.post0.dist-info/top_level.txt
ocstrack-0.1.4.post0.dist-info/RECORD
