Metadata-Version: 2.4
Name: ocstrack
Version: 0.1.4.post0
Summary: Satellite data download, crop, and collocation with model outputs
Author-email: Felicio Cassalho <felicio.cassalho@noaa.gov>
License: MIT
Project-URL: Homepage, https://github.com/noaa-ocs-modeling/OCSTrack
Project-URL: Repository, https://github.com/noaa-ocs-modeling/OCSTrack
Requires-Python: >=3.10
License-File: LICENSE.txt
Requires-Dist: numpy
Requires-Dist: xarray
Requires-Dist: scipy
Requires-Dist: tqdm
Requires-Dist: requests
Requires-Dist: netcdf4
Requires-Dist: h5netcdf
Requires-Dist: dask
Provides-Extra: dev
Requires-Dist: pytest>=6.0; extra == "dev"
Requires-Dist: pylint; extra == "dev"
Dynamic: license-file
